collectd_prometheus.py
collectd_prometheus-0.2.0.dist-info/LICENSE
collectd_prometheus-0.2.0.dist-info/WHEEL
collectd_prometheus-0.2.0.dist-info/METADATA
collectd_prometheus-0.2.0.dist-info/RECORD
