Metadata-Version: 2.1
Name: collectd-prometheus
Version: 0.2.0
Summary: collectd plugin to read Prometheus metrics endpoints
Home-page: https://github.com/ryarnyah/collectd-prometheus
License: Apache-2.0
Author: Ryar Nyah
Author-email: ryarnyah@gmail.com
Requires-Python: >=2.7, !=3.0.*, !=3.1.*, !=3.2.*, !=3.3.*, !=3.4.*, !=3.5.*
Classifier: License :: OSI Approved :: Apache Software License
Classifier: Programming Language :: Python :: 2
Classifier: Programming Language :: Python :: 2.7
Classifier: Programming Language :: Python :: 3
Classifier: Programming Language :: Python :: 3.10
Classifier: Programming Language :: Python :: 3.6
Classifier: Programming Language :: Python :: 3.7
Classifier: Programming Language :: Python :: 3.8
Classifier: Programming Language :: Python :: 3.9
Requires-Dist: prometheus-client (>=0.7.1,<0.8.0)
Requires-Dist: requests (>=2.25.1,<3.0.0)
Project-URL: Repository, https://github.com/ryarnyah/collectd-prometheus
